{
    "root": [
        {
            "name": "我的收藏",
            "id": "favorites",
            "length": " ..."
        },
        {
            "name": "大本诗歌",
            "id": "00001",
            "page": "0-50",
            "length": "786 个文件"
        },
        {
            "name": "补充本诗歌",
            "id": "00002",
            "page": "0-37",
            "length": "513 个文件"
        },
        {
            "name": "青年诗歌",
            "id": "00003",
            "page": "0-50",
            "length": "183 个文件"
        },
        {
            "name": "新歌颂咏",
            "id": "00004",
            "page": "0-39",
            "length": "164 个文件"
        },
        {
            "name": "2020诗歌总汇",
            "id": "00005",
            "length": "8 个文件"
        }
    ]
}